fmae/__init__.py
fmae/fmae_base.py
fmae/fmae_downscaling.py
fmae/fmae_tabular.py
fmae/fmae_upscaling.py
fmae/utilities.py
fmae-0.1.0.dist-info/licenses/LICENSE
fmae-0.1.0.dist-info/METADATA
fmae-0.1.0.dist-info/WHEEL
fmae-0.1.0.dist-info/top_level.txt
fmae-0.1.0.dist-info/RECORD
