Metadata-Version: 2.4
Name: fmae
Version: 0.1.0
Summary: This project provides the official Python library of FMAE (Fuzzy Model-Agnostic Explanation), which is a post-hoc XAI method designed to explain the decision-making behavior of pre-trained black-box predictive models.
Author-email: Faliang Yin <faliang.yin@gmail.com>, Hak-Keung Lam <hak-keung.lam@kcl.ac.uk>, David Watson <david.watson@kcl.ac.uk>
License: MIT License
Requires-Python: >=3.8
License-File: LICENSE
Requires-Dist: numpy
Requires-Dist: scikit-learn
Requires-Dist: matplotlib
Dynamic: license-file
